nvidia/dali/auto_aug/augmentations.py
nvidia/dali/auto_aug/rand_augment.py
nvidia/dali/internal.py
nvidia/dali/auto_aug/__init__.py
nvidia/dali/data_node.py
nvidia/dali/auto_aug/core/_augmentation.py
nvidia/dali/_typing.py
nvidia/dali/include/dali/kernels/kernel.h
nvidia/dali/include/dali/plugin/plugin_manager.h
nvidia/dali/plugin/tf.py
nvidia/dali/include/dali/kernels/normalize/normalize_cpu.h
nvidia/dali/include/dali/operators.h
nvidia/dali/include/dali/image/tiff_libtiff.h
nvidia/dali/include/dali/pipeline/executor/async_separated_pipelined_executor.h
nvidia/dali/include/dali/pipeline/operator/sequence_shape.h
nvidia/dali/include/dali/core/util.h
nvidia/dali/include/dali/pipeline/util/stream_pool.h
nvidia/dali/include/dali/imgcodec/parsers/jpeg.h
nvidia/dali/include/dali/pipeline/util/worker_thread.h
nvidia/dali/include/dali/operators/image/resize/resize_attr_base.h
nvidia/dali/include/dali/kernels/imgproc/geom/npp_remap_call.h
nvidia/dali/include/dali/pipeline/executor/executor_factory.h
nvidia/dali/include/dali/operators/image/crop/crop.h
nvidia/dali/include/dali/pipeline/operator/checkpointing/snapshot_serializer.h
nvidia/dali/include/dali/operators/imgcodec/peek_image_shape.h
nvidia/dali/include/dali/operators/audio/resample.h
nvidia/dali/include/dali/kernels/imgproc/resample/separable.h
nvidia/dali/include/dali/kernels/imgproc/color_manipulation/equalize/equalize.h
nvidia/dali/include/boost/preprocessor/repetition/detail/dmc/for.hpp
nvidia/dali/include/dali/operators/reader/loader/indexed_file_loader.h
nvidia/dali/include/dali/operators/reader/nvdecoder/cuviddec.h
nvidia/dali/include/dali/operators/bbox/bb_flip.cuh
nvidia/dali/include/dali/pipeline/data/meta.h
nvidia/dali/include/dali/pipeline/data/sample_view.h
nvidia/dali/include/dali/kernels/context.h
nvidia/dali/include/dali/kernels/signal/window/extract_windows_gpu.cuh
nvidia/dali/include/dali/kernels/imgproc/geom/remap.h
nvidia/dali/include/dali/kernels/imgproc/warp_cpu.h
nvidia_dali_cuda110-1.35.0.dist-info/WHEEL
nvidia_dali_cuda110-1.35.0.dist-info/METADATA
nvidia_dali_cuda110-1.35.0.dist-info/top_level.txt
nvidia_dali_cuda110-1.35.0.dist-info/entry_points.txt
nvidia_dali_cuda110-1.35.0.dist-info/RECORD
