Metadata-Version: 2.1
Name: nvidia-dali-cuda110
Version: 1.35.0
Summary: NVIDIA DALI  for CUDA 11.0. Git SHA: c420f32d5f5d899215e11f5d1c4b8f437b32dd95
Home-page: https://github.com/NVIDIA/dali
Author: NVIDIA Corporation
License: Apache License 2.0
Classifier: Programming Language :: Python :: 3.8
Classifier: Programming Language :: Python :: 3.9
Classifier: Programming Language :: Python :: 3.10
Classifier: Programming Language :: Python :: 3.11
Classifier: Programming Language :: Python :: 3.12
Requires-Python: >=3.8, <3.13
Requires-Dist: astunparse >=1.6.0
Requires-Dist: gast >=0.3.3
Requires-Dist: dm-tree
